[
    {
        "starred_at": "2017-05-25T19:48:50Z", 
        "user": {
            "following_url": "https://api.github.com/users/micahwoods/following{/other_user}", 
            "events_url": "https://api.github.com/users/micahwoods/events{/privacy}", 
            "organizations_url": "https://api.github.com/users/micahwoods/orgs", 
            "url": "https://api.github.com/users/micahwoods", 
            "gists_url": "https://api.github.com/users/micahwoods/gists{/gist_id}", 
            "html_url": "https://github.com/micahwoods", 
            "subscriptions_url": "https://api.github.com/users/micahwoods/subscriptions", 
            "avatar_url": "https://avatars1.githubusercontent.com/u/5830534?v=4", 
            "repos_url": "https://api.github.com/users/micahwoods/repos", 
            "received_events_url": "https://api.github.com/users/micahwoods/received_events", 
            "gravatar_id": "", 
            "starred_url": "https://api.github.com/users/micahwoods/starred{/owner}{/repo}", 
            "site_admin": false, 
            "login": "micahwoods", 
            "type": "User", 
            "id": 5830534, 
            "followers_url": "https://api.github.com/users/micahwoods/followers"
        }
    }, 
    {
        "starred_at": "2017-05-26T12:18:42Z", 
        "user": {
            "following_url": "https://api.github.com/users/zx8754/following{/other_user}", 
            "events_url": "https://api.github.com/users/zx8754/events{/privacy}", 
            "organizations_url": "https://api.github.com/users/zx8754/orgs", 
            "url": "https://api.github.com/users/zx8754", 
            "gists_url": "https://api.github.com/users/zx8754/gists{/gist_id}", 
            "html_url": "https://github.com/zx8754", 
            "subscriptions_url": "https://api.github.com/users/zx8754/subscriptions", 
            "avatar_url": "https://avatars0.githubusercontent.com/u/5212915?v=4", 
            "repos_url": "https://api.github.com/users/zx8754/repos", 
            "received_events_url": "https://api.github.com/users/zx8754/received_events", 
            "gravatar_id": "", 
            "starred_url": "https://api.github.com/users/zx8754/starred{/owner}{/repo}", 
            "site_admin": false, 
            "login": "zx8754", 
            "type": "User", 
            "id": 5212915, 
            "followers_url": "https://api.github.com/users/zx8754/followers"
        }
    }, 
    {
        "starred_at": "2017-05-26T12:33:34Z", 
        "user": {
            "following_url": "https://api.github.com/users/brodieG/following{/other_user}", 
            "events_url": "https://api.github.com/users/brodieG/events{/privacy}", 
            "organizations_url": "https://api.github.com/users/brodieG/orgs", 
            "url": "https://api.github.com/users/brodieG", 
            "gists_url": "https://api.github.com/users/brodieG/gists{/gist_id}", 
            "html_url": "https://github.com/brodieG", 
            "subscriptions_url": "https://api.github.com/users/brodieG/subscriptions", 
            "avatar_url": "https://avatars0.githubusercontent.com/u/6105908?v=4", 
            "repos_url": "https://api.github.com/users/brodieG/repos", 
            "received_events_url": "https://api.github.com/users/brodieG/received_events", 
            "gravatar_id": "", 
            "starred_url": "https://api.github.com/users/brodieG/starred{/owner}{/repo}", 
            "site_admin": false, 
            "login": "brodieG", 
            "type": "User", 
            "id": 6105908, 
            "followers_url": "https://api.github.com/users/brodieG/followers"
        }
    }, 
    {
        "starred_at": "2017-05-26T13:06:06Z", 
        "user": {
            "following_url": "https://api.github.com/users/jaapwalhout/following{/other_user}", 
            "events_url": "https://api.github.com/users/jaapwalhout/events{/privacy}", 
            "organizations_url": "https://api.github.com/users/jaapwalhout/orgs", 
            "url": "https://api.github.com/users/jaapwalhout", 
            "gists_url": "https://api.github.com/users/jaapwalhout/gists{/gist_id}", 
            "html_url": "https://github.com/jaapwalhout", 
            "subscriptions_url": "https://api.github.com/users/jaapwalhout/subscriptions", 
            "avatar_url": "https://avatars0.githubusercontent.com/u/1481150?v=4", 
            "repos_url": "https://api.github.com/users/jaapwalhout/repos", 
            "received_events_url": "https://api.github.com/users/jaapwalhout/received_events", 
            "gravatar_id": "", 
            "starred_url": "https://api.github.com/users/jaapwalhout/starred{/owner}{/repo}", 
            "site_admin": false, 
            "login": "jaapwalhout", 
            "type": "User", 
            "id": 1481150, 
            "followers_url": "https://api.github.com/users/jaapwalhout/followers"
        }
    }, 
    {
        "starred_at": "2017-06-19T21:54:28Z", 
        "user": {
            "following_url": "https://api.github.com/users/nacnudus/following{/other_user}", 
            "events_url": "https://api.github.com/users/nacnudus/events{/privacy}", 
            "organizations_url": "https://api.github.com/users/nacnudus/orgs", 
            "url": "https://api.github.com/users/nacnudus", 
            "gists_url": "https://api.github.com/users/nacnudus/gists{/gist_id}", 
            "html_url": "https://github.com/nacnudus", 
            "subscriptions_url": "https://api.github.com/users/nacnudus/subscriptions", 
            "avatar_url": "https://avatars1.githubusercontent.com/u/3522552?v=4", 
            "repos_url": "https://api.github.com/users/nacnudus/repos", 
            "received_events_url": "https://api.github.com/users/nacnudus/received_events", 
            "gravatar_id": "", 
            "starred_url": "https://api.github.com/users/nacnudus/starred{/owner}{/repo}", 
            "site_admin": false, 
            "login": "nacnudus", 
            "type": "User", 
            "id": 3522552, 
            "followers_url": "https://api.github.com/users/nacnudus/followers"
        }
    }, 
    {
        "starred_at": "2017-07-10T17:28:33Z", 
        "user": {
            "following_url": "https://api.github.com/users/johnfrye/following{/other_user}", 
            "events_url": "https://api.github.com/users/johnfrye/events{/privacy}", 
            "organizations_url": "https://api.github.com/users/johnfrye/orgs", 
            "url": "https://api.github.com/users/johnfrye", 
            "gists_url": "https://api.github.com/users/johnfrye/gists{/gist_id}", 
            "html_url": "https://github.com/johnfrye", 
            "subscriptions_url": "https://api.github.com/users/johnfrye/subscriptions", 
            "avatar_url": "https://avatars1.githubusercontent.com/u/7141373?v=4", 
            "repos_url": "https://api.github.com/users/johnfrye/repos", 
            "received_events_url": "https://api.github.com/users/johnfrye/received_events", 
            "gravatar_id": "", 
            "starred_url": "https://api.github.com/users/johnfrye/starred{/owner}{/repo}", 
            "site_admin": false, 
            "login": "johnfrye", 
            "type": "User", 
            "id": 7141373, 
            "followers_url": "https://api.github.com/users/johnfrye/followers"
        }
    }, 
    {
        "starred_at": "2017-07-13T10:32:49Z", 
        "user": {
            "following_url": "https://api.github.com/users/AlexIoannides/following{/other_user}", 
            "events_url": "https://api.github.com/users/AlexIoannides/events{/privacy}", 
            "organizations_url": "https://api.github.com/users/AlexIoannides/orgs", 
            "url": "https://api.github.com/users/AlexIoannides", 
            "gists_url": "https://api.github.com/users/AlexIoannides/gists{/gist_id}", 
            "html_url": "https://github.com/AlexIoannides", 
            "subscriptions_url": "https://api.github.com/users/AlexIoannides/subscriptions", 
            "avatar_url": "https://avatars2.githubusercontent.com/u/5968486?v=4", 
            "repos_url": "https://api.github.com/users/AlexIoannides/repos", 
            "received_events_url": "https://api.github.com/users/AlexIoannides/received_events", 
            "gravatar_id": "", 
            "starred_url": "https://api.github.com/users/AlexIoannides/starred{/owner}{/repo}", 
            "site_admin": false, 
            "login": "AlexIoannides", 
            "type": "User", 
            "id": 5968486, 
            "followers_url": "https://api.github.com/users/AlexIoannides/followers"
        }
    }, 
    {
        "starred_at": "2017-07-13T12:37:29Z", 
        "user": {
            "following_url": "https://api.github.com/users/silverstone1903/following{/other_user}", 
            "events_url": "https://api.github.com/users/silverstone1903/events{/privacy}", 
            "organizations_url": "https://api.github.com/users/silverstone1903/orgs", 
            "url": "https://api.github.com/users/silverstone1903", 
            "gists_url": "https://api.github.com/users/silverstone1903/gists{/gist_id}", 
            "html_url": "https://github.com/silverstone1903", 
            "subscriptions_url": "https://api.github.com/users/silverstone1903/subscriptions", 
            "avatar_url": "https://avatars1.githubusercontent.com/u/9806827?v=4", 
            "repos_url": "https://api.github.com/users/silverstone1903/repos", 
            "received_events_url": "https://api.github.com/users/silverstone1903/received_events", 
            "gravatar_id": "", 
            "starred_url": "https://api.github.com/users/silverstone1903/starred{/owner}{/repo}", 
            "site_admin": false, 
            "login": "silverstone1903", 
            "type": "User", 
            "id": 9806827, 
            "followers_url": "https://api.github.com/users/silverstone1903/followers"
        }
    }, 
    {
        "starred_at": "2017-07-14T23:09:04Z", 
        "user": {
            "following_url": "https://api.github.com/users/RobertMyles/following{/other_user}", 
            "events_url": "https://api.github.com/users/RobertMyles/events{/privacy}", 
            "organizations_url": "https://api.github.com/users/RobertMyles/orgs", 
            "url": "https://api.github.com/users/RobertMyles", 
            "gists_url": "https://api.github.com/users/RobertMyles/gists{/gist_id}", 
            "html_url": "https://github.com/RobertMyles", 
            "subscriptions_url": "https://api.github.com/users/RobertMyles/subscriptions", 
            "avatar_url": "https://avatars1.githubusercontent.com/u/7211207?v=4", 
            "repos_url": "https://api.github.com/users/RobertMyles/repos", 
            "received_events_url": "https://api.github.com/users/RobertMyles/received_events", 
            "gravatar_id": "", 
            "starred_url": "https://api.github.com/users/RobertMyles/starred{/owner}{/repo}", 
            "site_admin": false, 
            "login": "RobertMyles", 
            "type": "User", 
            "id": 7211207, 
            "followers_url": "https://api.github.com/users/RobertMyles/followers"
        }
    }, 
    {
        "starred_at": "2017-07-14T23:28:58Z", 
        "user": {
            "following_url": "https://api.github.com/users/danilofreire/following{/other_user}", 
            "events_url": "https://api.github.com/users/danilofreire/events{/privacy}", 
            "organizations_url": "https://api.github.com/users/danilofreire/orgs", 
            "url": "https://api.github.com/users/danilofreire", 
            "gists_url": "https://api.github.com/users/danilofreire/gists{/gist_id}", 
            "html_url": "https://github.com/danilofreire", 
            "subscriptions_url": "https://api.github.com/users/danilofreire/subscriptions", 
            "avatar_url": "https://avatars1.githubusercontent.com/u/4510022?v=4", 
            "repos_url": "https://api.github.com/users/danilofreire/repos", 
            "received_events_url": "https://api.github.com/users/danilofreire/received_events", 
            "gravatar_id": "", 
            "starred_url": "https://api.github.com/users/danilofreire/starred{/owner}{/repo}", 
            "site_admin": false, 
            "login": "danilofreire", 
            "type": "User", 
            "id": 4510022, 
            "followers_url": "https://api.github.com/users/danilofreire/followers"
        }
    }, 
    {
        "starred_at": "2017-07-16T13:48:19Z", 
        "user": {
            "following_url": "https://api.github.com/users/RMHogervorst/following{/other_user}", 
            "events_url": "https://api.github.com/users/RMHogervorst/events{/privacy}", 
            "organizations_url": "https://api.github.com/users/RMHogervorst/orgs", 
            "url": "https://api.github.com/users/RMHogervorst", 
            "gists_url": "https://api.github.com/users/RMHogervorst/gists{/gist_id}", 
            "html_url": "https://github.com/RMHogervorst", 
            "subscriptions_url": "https://api.github.com/users/RMHogervorst/subscriptions", 
            "avatar_url": "https://avatars0.githubusercontent.com/u/9538040?v=4", 
            "repos_url": "https://api.github.com/users/RMHogervorst/repos", 
            "received_events_url": "https://api.github.com/users/RMHogervorst/received_events", 
            "gravatar_id": "", 
            "starred_url": "https://api.github.com/users/RMHogervorst/starred{/owner}{/repo}", 
            "site_admin": false, 
            "login": "RMHogervorst", 
            "type": "User", 
            "id": 9538040, 
            "followers_url": "https://api.github.com/users/RMHogervorst/followers"
        }
    }, 
    {
        "starred_at": "2017-07-20T20:23:18Z", 
        "user": {
            "following_url": "https://api.github.com/users/briatte/following{/other_user}", 
            "events_url": "https://api.github.com/users/briatte/events{/privacy}", 
            "organizations_url": "https://api.github.com/users/briatte/orgs", 
            "url": "https://api.github.com/users/briatte", 
            "gists_url": "https://api.github.com/users/briatte/gists{/gist_id}", 
            "html_url": "https://github.com/briatte", 
            "subscriptions_url": "https://api.github.com/users/briatte/subscriptions", 
            "avatar_url": "https://avatars2.githubusercontent.com/u/322533?v=4", 
            "repos_url": "https://api.github.com/users/briatte/repos", 
            "received_events_url": "https://api.github.com/users/briatte/received_events", 
            "gravatar_id": "", 
            "starred_url": "https://api.github.com/users/briatte/starred{/owner}{/repo}", 
            "site_admin": false, 
            "login": "briatte", 
            "type": "User", 
            "id": 322533, 
            "followers_url": "https://api.github.com/users/briatte/followers"
        }
    }, 
    {
        "starred_at": "2017-07-20T21:19:52Z", 
        "user": {
            "following_url": "https://api.github.com/users/jbkunst/following{/other_user}", 
            "events_url": "https://api.github.com/users/jbkunst/events{/privacy}", 
            "organizations_url": "https://api.github.com/users/jbkunst/orgs", 
            "url": "https://api.github.com/users/jbkunst", 
            "gists_url": "https://api.github.com/users/jbkunst/gists{/gist_id}", 
            "html_url": "https://github.com/jbkunst", 
            "subscriptions_url": "https://api.github.com/users/jbkunst/subscriptions", 
            "avatar_url": "https://avatars0.githubusercontent.com/u/56481?v=4", 
            "repos_url": "https://api.github.com/users/jbkunst/repos", 
            "received_events_url": "https://api.github.com/users/jbkunst/received_events", 
            "gravatar_id": "", 
            "starred_url": "https://api.github.com/users/jbkunst/starred{/owner}{/repo}", 
            "site_admin": false, 
            "login": "jbkunst", 
            "type": "User", 
            "id": 56481, 
            "followers_url": "https://api.github.com/users/jbkunst/followers"
        }
    }, 
    {
        "starred_at": "2017-07-21T09:50:25Z", 
        "user": {
            "following_url": "https://api.github.com/users/safferli/following{/other_user}", 
            "events_url": "https://api.github.com/users/safferli/events{/privacy}", 
            "organizations_url": "https://api.github.com/users/safferli/orgs", 
            "url": "https://api.github.com/users/safferli", 
            "gists_url": "https://api.github.com/users/safferli/gists{/gist_id}", 
            "html_url": "https://github.com/safferli", 
            "subscriptions_url": "https://api.github.com/users/safferli/subscriptions", 
            "avatar_url": "https://avatars2.githubusercontent.com/u/2768881?v=4", 
            "repos_url": "https://api.github.com/users/safferli/repos", 
            "received_events_url": "https://api.github.com/users/safferli/received_events", 
            "gravatar_id": "", 
            "starred_url": "https://api.github.com/users/safferli/starred{/owner}{/repo}", 
            "site_admin": false, 
            "login": "safferli", 
            "type": "User", 
            "id": 2768881, 
            "followers_url": "https://api.github.com/users/safferli/followers"
        }
    }, 
    {
        "starred_at": "2017-07-24T05:49:40Z", 
        "user": {
            "following_url": "https://api.github.com/users/personlin/following{/other_user}", 
            "events_url": "https://api.github.com/users/personlin/events{/privacy}", 
            "organizations_url": "https://api.github.com/users/personlin/orgs", 
            "url": "https://api.github.com/users/personlin", 
            "gists_url": "https://api.github.com/users/personlin/gists{/gist_id}", 
            "html_url": "https://github.com/personlin", 
            "subscriptions_url": "https://api.github.com/users/personlin/subscriptions", 
            "avatar_url": "https://avatars1.githubusercontent.com/u/36533?v=4", 
            "repos_url": "https://api.github.com/users/personlin/repos", 
            "received_events_url": "https://api.github.com/users/personlin/received_events", 
            "gravatar_id": "", 
            "starred_url": "https://api.github.com/users/personlin/starred{/owner}{/repo}", 
            "site_admin": false, 
            "login": "personlin", 
            "type": "User", 
            "id": 36533, 
            "followers_url": "https://api.github.com/users/personlin/followers"
        }
    }, 
    {
        "starred_at": "2017-07-24T17:31:38Z", 
        "user": {
            "following_url": "https://api.github.com/users/dnbarron/following{/other_user}", 
            "events_url": "https://api.github.com/users/dnbarron/events{/privacy}", 
            "organizations_url": "https://api.github.com/users/dnbarron/orgs", 
            "url": "https://api.github.com/users/dnbarron", 
            "gists_url": "https://api.github.com/users/dnbarron/gists{/gist_id}", 
            "html_url": "https://github.com/dnbarron", 
            "subscriptions_url": "https://api.github.com/users/dnbarron/subscriptions", 
            "avatar_url": "https://avatars2.githubusercontent.com/u/1565592?v=4", 
            "repos_url": "https://api.github.com/users/dnbarron/repos", 
            "received_events_url": "https://api.github.com/users/dnbarron/received_events", 
            "gravatar_id": "", 
            "starred_url": "https://api.github.com/users/dnbarron/starred{/owner}{/repo}", 
            "site_admin": false, 
            "login": "dnbarron", 
            "type": "User", 
            "id": 1565592, 
            "followers_url": "https://api.github.com/users/dnbarron/followers"
        }
    }, 
    {
        "starred_at": "2017-08-06T12:41:32Z", 
        "user": {
            "following_url": "https://api.github.com/users/Cloud2016/following{/other_user}", 
            "events_url": "https://api.github.com/users/Cloud2016/events{/privacy}", 
            "organizations_url": "https://api.github.com/users/Cloud2016/orgs", 
            "url": "https://api.github.com/users/Cloud2016", 
            "gists_url": "https://api.github.com/users/Cloud2016/gists{/gist_id}", 
            "html_url": "https://github.com/Cloud2016", 
            "subscriptions_url": "https://api.github.com/users/Cloud2016/subscriptions", 
            "avatar_url": "https://avatars2.githubusercontent.com/u/12031874?v=4", 
            "repos_url": "https://api.github.com/users/Cloud2016/repos", 
            "received_events_url": "https://api.github.com/users/Cloud2016/received_events", 
            "gravatar_id": "", 
            "starred_url": "https://api.github.com/users/Cloud2016/starred{/owner}{/repo}", 
            "site_admin": false, 
            "login": "Cloud2016", 
            "type": "User", 
            "id": 12031874, 
            "followers_url": "https://api.github.com/users/Cloud2016/followers"
        }
    }, 
    {
        "starred_at": "2017-11-30T16:46:54Z", 
        "user": {
            "following_url": "https://api.github.com/users/jemus42/following{/other_user}", 
            "events_url": "https://api.github.com/users/jemus42/events{/privacy}", 
            "organizations_url": "https://api.github.com/users/jemus42/orgs", 
            "url": "https://api.github.com/users/jemus42", 
            "gists_url": "https://api.github.com/users/jemus42/gists{/gist_id}", 
            "html_url": "https://github.com/jemus42", 
            "subscriptions_url": "https://api.github.com/users/jemus42/subscriptions", 
            "avatar_url": "https://avatars3.githubusercontent.com/u/1613346?v=4", 
            "repos_url": "https://api.github.com/users/jemus42/repos", 
            "received_events_url": "https://api.github.com/users/jemus42/received_events", 
            "gravatar_id": "", 
            "starred_url": "https://api.github.com/users/jemus42/starred{/owner}{/repo}", 
            "site_admin": false, 
            "login": "jemus42", 
            "type": "User", 
            "id": 1613346, 
            "followers_url": "https://api.github.com/users/jemus42/followers"
        }
    }
]